PySQLiteDBConnection
