Metadata-Version: 2.1
Name: PySQLiteDBConnection
Version: 1.0.9
Summary: Este paquete proporciona una clase `Connect` para gestionar bases de datos SQLite3 de manera sencilla y estandarizada.
Home-page: https://github.com/SurivZ/Py-SQLite-DB-Connection
Author: SurivZ
Author-email: franklinserrano23@email.com
Classifier: Development Status :: 5 - Production/Stable
Classifier: Intended Audience :: Developers
Classifier: License :: OSI Approved :: MIT License
Classifier: Operating System :: OS Independent
Classifier: Programming Language :: Python :: 3
Classifier: Programming Language :: Python :: 3.7
Classifier: Programming Language :: Python :: 3.8
Classifier: Programming Language :: Python :: 3.9
Classifier: Programming Language :: Python :: 3.10
Classifier: Topic :: Software Development :: Libraries :: Python Modules
Requires-Python: >=3.7
